laplax/__init__.py
laplax/api.py
laplax/enums.py
laplax/register.py
laplax/types.py
laplax/curv/__init__.py
laplax/curv/cov.py
laplax/curv/diagonal.py
laplax/curv/full.py
laplax/curv/ggn.py
laplax/curv/hessian.py
laplax/curv/lanczos.py
laplax/curv/lobpcg.py
laplax/curv/low_rank.py
laplax/curv/utils.py
laplax/eval/__init__.py
laplax/eval/calibrate.py
laplax/eval/likelihood.py
laplax/eval/metrics.py
laplax/eval/predictives.py
laplax/eval/pushforward.py
laplax/eval/utils.py
laplax/util/__init__.py
laplax/util/flatten.py
laplax/util/loader.py
laplax/util/mv.py
laplax/util/ops.py
laplax/util/tree.py
laplax/util/utils.py
laplax-0.0.2.dist-info/METADATA
laplax-0.0.2.dist-info/WHEEL
laplax-0.0.2.dist-info/licenses/LICENSE
laplax-0.0.2.dist-info/RECORD
