Metadata-Version: 2.4
Name: laplax
Version: 0.0.2
Summary: Laplace approximations in JAX.
Project-URL: Repository, https://github.com/laplax-org/laplax
Author: Tobias Weber, Bálint Mucsányi
License: MIT License
License-File: LICENSE
Classifier: Development Status :: 3 - Alpha
Classifier: Intended Audience :: Information Technology
Classifier: Intended Audience :: Science/Research
Classifier: License :: OSI Approved :: MIT License
Classifier: Natural Language :: English
Classifier: Operating System :: OS Independent
Classifier: Programming Language :: Python :: 3
Classifier: Programming Language :: Python :: 3 :: Only
Classifier: Programming Language :: Python :: 3.11
Classifier: Programming Language :: Python :: 3.12
Classifier: Programming Language :: Python :: 3.13
Classifier: Topic :: Scientific/Engineering :: Artificial Intelligence
Classifier: Topic :: Scientific/Engineering :: Information Analysis
Classifier: Topic :: Scientific/Engineering :: Mathematics
Requires-Python: <3.14,>=3.11
Requires-Dist: jax
Requires-Dist: jaxtyping
Requires-Dist: loguru
Requires-Dist: tqdm
Provides-Extra: dev
Requires-Dist: coveralls; extra == 'dev'
Requires-Dist: curvlinops-for-pytorch; extra == 'dev'
Requires-Dist: equinox; extra == 'dev'
Requires-Dist: flax; extra == 'dev'
Requires-Dist: jupyterlab; extra == 'dev'
Requires-Dist: laplace-torch; extra == 'dev'
Requires-Dist: matplotlib; extra == 'dev'
Requires-Dist: pre-commit; extra == 'dev'
Requires-Dist: pyright; extra == 'dev'
Requires-Dist: pytest; extra == 'dev'
Requires-Dist: pytest-cases; extra == 'dev'
Requires-Dist: pytest-cov; extra == 'dev'
Requires-Dist: ruff; extra == 'dev'
Requires-Dist: torch; extra == 'dev'
Requires-Dist: tox-uv; extra == 'dev'
Provides-Extra: docs
Requires-Dist: mkdocs; extra == 'docs'
Requires-Dist: mkdocs-autorefs; extra == 'docs'
Requires-Dist: mkdocs-bibtex; extra == 'docs'
Requires-Dist: mkdocs-gen-files; extra == 'docs'
Requires-Dist: mkdocs-material; extra == 'docs'
Requires-Dist: mkdocstrings; extra == 'docs'
Requires-Dist: mkdocstrings-python; extra == 'docs'
Requires-Dist: mknotebooks; extra == 'docs'
Requires-Dist: pytkdocs-tweaks; extra == 'docs'
Provides-Extra: notebooks
Requires-Dist: flax; extra == 'notebooks'
Requires-Dist: ipywidgets; extra == 'notebooks'
Requires-Dist: optax; extra == 'notebooks'
Requires-Dist: pandas; extra == 'notebooks'
Requires-Dist: skerch; extra == 'notebooks'
Requires-Dist: torch; extra == 'notebooks'
Requires-Dist: torchvision; extra == 'notebooks'
Requires-Dist: tueplots; extra == 'notebooks'
Requires-Dist: wandb; extra == 'notebooks'
